AUTHORS.rst
CONTRIBUTING.rst
HISTORY.rst
MANIFEST.in
README.rst
setup.cfg
setup.py
docs/Makefile
docs/authors.rst
docs/conf.py
docs/contributing.rst
docs/history.rst
docs/index.rst
docs/installation.rst
docs/make.bat
docs/readme.rst
docs/usage.rst
tank_forecaster/__init__.py
tank_forecaster/cli.py
tank_forecaster/decomp.py
tank_forecaster/forecaster.py
tank_forecaster/validation.py
tank_forecaster.egg-info/PKG-INFO
tank_forecaster.egg-info/SOURCES.txt
tank_forecaster.egg-info/dependency_links.txt
tank_forecaster.egg-info/entry_points.txt
tank_forecaster.egg-info/not-zip-safe
tank_forecaster.egg-info/requires.txt
tank_forecaster.egg-info/top_level.txt
tests/__init__.py
tests/conftest.py
tests/test_decomp_holiday.py
tests/test_decomp_sales.py
tests/test_decomp_tank.py
tests/test_forecast_far.py
tests/test_forecast_near.py
tests/test_formatting.py