Metadata-Version: 1.2
Name: tank-forecaster
Version: 0.3.56
Summary: small package for generating forecasts for gas tanks
Home-page: https://www.capspire.com
Author: Jim Vogel
Author-email: james.vogel@capspire.com
License: UNKNOWN
Keywords: tank_forecaster
Platform: UNKNOWN
Classifier: Development Status :: 2 - Pre-Alpha
Classifier: Intended Audience :: Developers
Classifier: Natural Language :: English
Classifier: Programming Language :: Python :: 3.8
Classifier: Programming Language :: Python :: 3.7
Classifier: Programming Language :: Python :: 3.6
Requires-Python: >=3.6
